{
    "1": {
        "think": [
            "患者术后第一天，心率加快、四肢较凉，腹腔引流暗红色液体875ml，考虑术后出血；患者0927血红蛋白从115降至75，仍然提示术后出血，需要输血治疗",
            "20240930:B型钠尿肽前体(NTproBNP)测定(发光法) 1269.0 pg/mL （急性呼吸困难诊断为心衰临界值: 5075岁,NTproBNP＞900pg/ml ），20241005 12:29影像诊断 左肺下叶前内基底段肺动脉少许肺栓塞；肺动脉期下腔静脉及肝静脉内对比剂逆流显影，需注意右心功能不全。",
            "WBC、PCT持续多日升高，20241005影像诊断：术区周围渗出，胃空肠吻合口周围并包裹性积液，20241008在超声引导下行穿刺置管（猪尾巴管），持续流质饮食，直至出院"
        ],
        "complications": [
            {
                "name": "术后出血",
                "grading": "中"
            },
            {
                "name": "肺栓塞",
                "grading": "轻"
            },
            {
                "name": "吻合口破裂",
                "grading": "中"
            }
        ]
    }
}